volux/__init__.py
volux/__version__.py
volux/demo.py
volux/exceptions.py
volux/module/__init__.py
volux/types.py
volux/util/__init__.py
volux/util/linux.py
volux/util/suppress.py
volux-0.11.2.dist-info/METADATA
volux-0.11.2.dist-info/WHEEL
volux-0.11.2.dist-info/RECORD
