Metadata-Version: 2.1
Name: volux
Version: 0.11.2
Summary: Modular system for creating entertainment workflows with local, attached or network devices
Home-page: https://gitlab.com/volux/volux/
License: AGPLv3
Author: DrTexx
Author-email: denver.opensource@tutanota.com
Requires-Python: >=3.8.1,<4.0.0
Classifier: License :: Other/Proprietary License
Classifier: Programming Language :: Python :: 3
Classifier: Programming Language :: Python :: 3.9
Classifier: Programming Language :: Python :: 3.10
Classifier: Programming Language :: Python :: 3.11
Requires-Dist: numpy (>=1.23,<2.0)
Project-URL: Repository, https://gitlab.com/volux/volux/
